filtro/__init__.py
filtro/api_client.py
filtro-0.1.3.dist-info/METADATA
filtro-0.1.3.dist-info/WHEEL
filtro-0.1.3.dist-info/RECORD
