Metadata-Version: 2.1
Name: filtro
Version: 0.1.3
Summary: The official filtro python package.
Author: Andrea Pinto
Author-email: andrea@filtro.ai
Requires-Python: >=3.9,<4.0
Classifier: Programming Language :: Python :: 3
Classifier: Programming Language :: Python :: 3.9
Classifier: Programming Language :: Python :: 3.10
Classifier: Programming Language :: Python :: 3.11
Requires-Dist: pydantic (>=1.10.9,<2.0.0)
Requires-Dist: requests (>=2.31.0,<3.0.0)
